odoo/addons/hr_attendance_user_list/README.rst
odoo/addons/hr_attendance_user_list/__init__.py
odoo/addons/hr_attendance_user_list/__manifest__.py
odoo/addons/hr_attendance_user_list/i18n/es.po
odoo/addons/hr_attendance_user_list/i18n/hr_attendance_user_list.pot
odoo/addons/hr_attendance_user_list/i18n/it.po
odoo/addons/hr_attendance_user_list/readme/CONTRIBUTORS.rst
odoo/addons/hr_attendance_user_list/readme/DESCRIPTION.rst
odoo/addons/hr_attendance_user_list/readme/USAGE.rst
odoo/addons/hr_attendance_user_list/static/description/icon.png
odoo/addons/hr_attendance_user_list/static/description/index.html
odoo/addons/hr_attendance_user_list/views/hr_attendance_view.xml
odoo13_addon_hr_attendance_user_list-13.0.1.0.1.dev6.dist-info/METADATA
odoo13_addon_hr_attendance_user_list-13.0.1.0.1.dev6.dist-info/WHEEL
odoo13_addon_hr_attendance_user_list-13.0.1.0.1.dev6.dist-info/top_level.txt
odoo13_addon_hr_attendance_user_list-13.0.1.0.1.dev6.dist-info/RECORD
